ruclip/__init__.py
ruclip/model.py
ruclip/predictor.py
ruclip/processor.py
ruclip-0.0.2.dist-info/LICENSE.txt
ruclip-0.0.2.dist-info/METADATA
ruclip-0.0.2.dist-info/WHEEL
ruclip-0.0.2.dist-info/top_level.txt
ruclip-0.0.2.dist-info/RECORD
