Metadata-Version: 2.1
Name: ruclip
Version: 0.0.2
Summary: RuCLIP: Zero-shot image classification models for Russian language
Home-page: UNKNOWN
Author: SberAI, SberDevices
Author-email: shonenkov@phystech.edu
License: UNKNOWN
Platform: UNKNOWN
License-File: LICENSE.txt
Requires-Dist: torch
Requires-Dist: torchvision
Requires-Dist: huggingface-hub (==0.2.1)
Requires-Dist: youtokentome (~=1.0.6)
Requires-Dist: more-itertools (==8.12.0)
